example_app/__init__.py
example_app/example.py
kildiesel_app_kc-0.0.30.dist-info/METADATA
kildiesel_app_kc-0.0.30.dist-info/WHEEL
kildiesel_app_kc-0.0.30.dist-info/top_level.txt
kildiesel_app_kc-0.0.30.dist-info/RECORD
